openblog-3.0.1.dist-info/licenses/LICENSE
pipeline/__init__.py
pipeline/config.py
pipeline/agents/__init__.py
pipeline/agents/asset_finder.py
pipeline/agents/chart_generator.py
pipeline/agents/enhanced_asset_finder.py
pipeline/agents/google_images_finder.py
pipeline/agents/serper_images_finder.py
pipeline/agents/shadcn_chart_generator.py
pipeline/agents/simple_chart_generator.py
pipeline/blog_generation/__init__.py
pipeline/blog_generation/stage_00_data_fetch.py
pipeline/blog_generation/stage_01_prompt_build.py
pipeline/blog_generation/stage_02_gemini_call.py
pipeline/blog_generation/stage_03_quality_refinement.py
pipeline/blog_generation/stage_04_citations.py
pipeline/blog_generation/stage_05_internal_links.py
pipeline/blog_generation/stage_06_image.py
pipeline/blog_generation/stage_06_toc.py
pipeline/blog_generation/stage_07_metadata.py
pipeline/blog_generation/stage_07_similarity_check.py
pipeline/blog_generation/stage_08_cleanup.py
pipeline/blog_generation/stage_08_faq_paa.py
pipeline/blog_generation/stage_09_storage.py
pipeline/blog_generation/stage_12_review_iteration.py
pipeline/core/__init__.py
pipeline/core/company_context.py
pipeline/core/error_handling.py
pipeline/core/execution_context.py
pipeline/core/job_manager.py
pipeline/core/quality_monitor.py
pipeline/core/regeneration_engine.py
pipeline/core/stage_factory.py
pipeline/core/workflow_engine.py
pipeline/data_sources/__init__.py
pipeline/data_sources/sitemap_crawler.py
pipeline/data_sources/sitemap_page.py
pipeline/data_sources/test_sitemap_crawler.py
pipeline/examples/__init__.py
pipeline/examples/company_context_examples.py
pipeline/integrations/__init__.py
pipeline/integrations/regeneration_integration.py
pipeline/integrations/seranking/__init__.py
pipeline/integrations/seranking/gap_analyzer.py
pipeline/integrations/seranking/gap_analyzer_wrapper.py
pipeline/integrations/seranking/seranking_client.py
pipeline/keyword_generation/__init__.py
pipeline/keyword_generation/adapter.py
pipeline/keyword_generation/ai_generator.py
openblog-3.0.1.dist-info/METADATA
openblog-3.0.1.dist-info/WHEEL
openblog-3.0.1.dist-info/entry_points.txt
openblog-3.0.1.dist-info/top_level.txt
openblog-3.0.1.dist-info/RECORD
