Metadata-Version: 2.4
Name: openblog
Version: 3.0.1
Summary: AI-powered blog generation from your terminal. Create SEO-optimized, publication-ready articles with a single command.
Author-email: OpenBlog Contributors <hello@openblog.dev>
License: MIT
Project-URL: Homepage, https://github.com/federicodeponte/openblog
Project-URL: Documentation, https://github.com/federicodeponte/openblog#readme
Project-URL: Repository, https://github.com/federicodeponte/openblog
Project-URL: Issues, https://github.com/federicodeponte/openblog/issues
Keywords: blog,ai,content-generation,seo,writing,cli,gemini,article,automation
Classifier: Development Status :: 4 - Beta
Classifier: Environment :: Console
Classifier: Intended Audience :: Developers
Classifier: Intended Audience :: End Users/Desktop
Classifier: License :: OSI Approved :: MIT License
Classifier: Operating System :: OS Independent
Classifier: Programming Language :: Python :: 3
Classifier: Programming Language :: Python :: 3.9
Classifier: Programming Language :: Python :: 3.10
Classifier: Programming Language :: Python :: 3.11
Classifier: Programming Language :: Python :: 3.12
Classifier: Topic :: Text Processing :: General
Classifier: Topic :: Internet :: WWW/HTTP :: Dynamic Content
Classifier: Typing :: Typed
Requires-Python: >=3.9
License-File: LICENSE
Requires-Dist: typer>=0.9.0
Requires-Dist: rich>=13.0.0
Requires-Dist: google-genai>=1.0.0
Provides-Extra: server
Requires-Dist: fastapi>=0.104.0; extra == "server"
Requires-Dist: uvicorn[standard]>=0.24.0; extra == "server"
Requires-Dist: slowapi>=0.1.9; extra == "server"
Requires-Dist: bleach>=6.0.0; extra == "server"
Requires-Dist: lxml>=4.9.0; extra == "server"
Requires-Dist: defusedxml>=0.7.0; extra == "server"
Requires-Dist: pillow>=10.0.0; extra == "server"
Requires-Dist: playwright>=1.40.0; extra == "server"
Requires-Dist: langdetect>=1.0.9; extra == "server"
Requires-Dist: google-api-python-client>=2.108.0; extra == "server"
Requires-Dist: google-auth>=2.24.0; extra == "server"
Provides-Extra: dev
Requires-Dist: pytest>=7.4.0; extra == "dev"
Requires-Dist: pytest-asyncio>=0.21.0; extra == "dev"
Requires-Dist: black>=23.0.0; extra == "dev"
Requires-Dist: mypy>=1.5.0; extra == "dev"
Requires-Dist: ruff>=0.1.0; extra == "dev"
Provides-Extra: all
Requires-Dist: openblog[dev,server]; extra == "all"
Dynamic: license-file
